sncl/__init__.py
sncl/airtable.py
sncl/airtable_async.py
sncl/wompi_async.py
sncl-1.2.0.dist-info/LICENSE
sncl-1.2.0.dist-info/METADATA
sncl-1.2.0.dist-info/WHEEL
sncl-1.2.0.dist-info/top_level.txt
sncl-1.2.0.dist-info/RECORD
