Metadata-Version: 2.2
Name: sncl
Version: 1.2.0
Summary: A utility library for API interactions including Wompi payments and Airtable
Home-page: https://github.com/sashanclrp/sncl-personal-libraries
Author: Sasha Nicolai Canal
Author-email: Sasha Nicolai Canal <sasha@candyflip.co>
License: MIT License
Project-URL: Homepage, https://github.com/sashanclrp/sncl-personal-libraries
Project-URL: Issues, https://github.com/sashanclrp/sncl-personal-libraries/issues
Classifier: Programming Language :: Python :: 3
Classifier: License :: OSI Approved :: MIT License
Classifier: Operating System :: OS Independent
Requires-Python: >=3.6
License-File: LICENSE
Requires-Dist: requests
Requires-Dist: pandas
Requires-Dist: typing
Requires-Dist: aiohttp
Requires-Dist: asyncio
Dynamic: author
Dynamic: home-page
Dynamic: requires-python
